{"avatars":[{"allow_promotion":true,"allow_remixing":false,"attributions":{"creator":"Hubs Team"},"avatar_id":"HvAFr6U","base_gltf_url":"https://hubs.mozilla.com/api/v1/avatars/HvAFr6U/base.gltf?v=63818755467","description":null,"files":{"base_map":"https://uploads-prod.reticulum.io/files/7abbdb8b-2ec9-4252-9ffb-a7816991200b.png","bin":"https://uploads-prod.reticulum.io/files/f962889d-9b26-4c91-bd3b-5b5b86d544cc.bin","emissive_map":null,"gltf":"https://uploads-prod.reticulum.io/files/d659f697-9068-41fb-8b78-dfcd2376a5c0","normal_map":null,"orm_map":null,"thumbnail":"https://uploads-prod.reticulum.io/files/b57e48c3-055e-4033-9a6d-472afd5bd113.png"},"gltf_url":"https://hubs.mozilla.com/api/v1/avatars/HvAFr6U/avatar.gltf?v=63818755467","name":"Astronaut_LightPurple","parent_avatar_listing_id":null,"type":"avatar_listing"}]}
