{"avatars":[{"allow_promotion":true,"allow_remixing":false,"attributions":{"creator":"Hubs Team"},"avatar_id":"vXTG8Rz","base_gltf_url":"https://hubs.mozilla.com/api/v1/avatars/vXTG8Rz/base.gltf?v=63848963278","description":null,"files":{"base_map":null,"bin":"https://uploads-prod.reticulum.io/files/01319a2b-c8a6-4f7c-8918-7351aa74ad65.bin","emissive_map":null,"gltf":"https://uploads-prod.reticulum.io/files/014088c1-a924-43b6-9dff-4e695a4e4ae8","normal_map":null,"orm_map":null,"thumbnail":"https://uploads-prod.reticulum.io/files/2da284ee-1a72-4989-bb01-8ed7a7b851a2.png"},"gltf_url":"https://hubs.mozilla.com/api/v1/avatars/vXTG8Rz/avatar.gltf?v=63848963278","name":"Food - Corn Dog","parent_avatar_listing_id":null,"type":"avatar_listing"}]}
