{"avatars":[{"allow_promotion":true,"allow_remixing":false,"attributions":{"creator":"Hubs Team"},"avatar_id":"mbWkB9T","base_gltf_url":"https://hubs.mozilla.com/api/v1/avatars/mbWkB9T/base.gltf?v=63848963263","description":null,"files":{"base_map":null,"bin":"https://uploads-prod.reticulum.io/files/19a43397-c061-4912-ba93-95002080a59a.bin","emissive_map":null,"gltf":"https://uploads-prod.reticulum.io/files/557235b8-f24b-4aa8-9382-a5802aff018c","normal_map":null,"orm_map":null,"thumbnail":"https://uploads-prod.reticulum.io/files/4b294ca1-6a0d-4913-8329-e5fee22452bc.png"},"gltf_url":"https://hubs.mozilla.com/api/v1/avatars/mbWkB9T/avatar.gltf?v=63848963263","name":"Food - Strawberry","parent_avatar_listing_id":null,"type":"avatar_listing"}]}
