{"avatars":[{"allow_promotion":true,"allow_remixing":true,"attributions":{"creator":"JCo"},"avatar_id":"G8jyym2","base_gltf_url":"https://hubs.mozilla.com/api/v1/avatars/G8jyym2/base.gltf?v=63726570330","description":null,"files":{"base_map":"https://uploads-prod.reticulum.io/files/cdd0b8c4-7604-4915-9c93-bd37649ecaec.png","bin":null,"emissive_map":"https://uploads-prod.reticulum.io/files/f8cc81c4-e909-4c5d-b73c-0d7dda101d60.png","gltf":null,"normal_map":"https://uploads-prod.reticulum.io/files/c0a0cff1-55ff-4a5a-b1b5-8b6f7b58bfe9.png","orm_map":"https://uploads-prod.reticulum.io/files/0f2a6c0f-0d71-4f58-b7f0-66b1e12ae0aa.png","thumbnail":"https://uploads-prod.reticulum.io/files/6959f7b8-bf5d-4e63-bf19-02ead2e36543.png"},"gltf_url":"https://hubs.mozilla.com/api/v1/avatars/G8jyym2/avatar.gltf?v=63726570330","name":"Suit Casual Miami","parent_avatar_listing_id":"basebot","type":"avatar_listing"}]}
