{"scenes":[{"account_id":false,"allow_promotion":true,"allow_remixing":true,"attribution":null,"attributions":{"content":[{"author":"mozillareality","name":"Light Fixture - Ceiling Recessed","url":"https://sketchfab.com/models/269fd427629548a8a0949a6493c5b223"},{"author":"roughdominator","name":"Sconce","url":"https://sketchfab.com/3d-models/sconce-04547d663fe14f3b853e3b6341ef100e"}],"creator":"JCo"},"description":null,"model_url":"https://uploads-prod.reticulum.io/files/3adceb98-0a2a-4b39-bafe-24e62b10eb8c.bin","name":"MaterialExamples","parent_scene_id":null,"project_id":null,"scene_id":"i8GOGEz","scene_project_url":"https://uploads-prod.reticulum.io/files/f70eae42-74a1-4da0-b5eb-8f322124e4a1.json","screenshot_url":"https://uploads-prod.reticulum.io/files/ec18165a-5d48-47ae-8dfc-bcb22b10a51b.jpg","type":"scene_listing","url":"https://hubs.mozilla.com/scenes/i8GOGEz/materialexamples"}]}
