{"scenes":[{"account_id":false,"allow_promotion":true,"allow_remixing":true,"attribution":null,"attributions":{"content":[{"author":"","url":"https://uploads-prod.reticulum.io/files/c1bb511c-7b58-46b3-8ec2-517adf1783d3.glb"}],"creator":"JCo"},"description":null,"model_url":"https://uploads-prod.reticulum.io/files/62f265ce-4910-4cf7-b157-6307674dcd4a.bin","name":"ScrollyRoom","parent_scene_id":null,"project_id":"maQTuzZ","scene_id":"pROJc5X","scene_project_url":"https://uploads-prod.reticulum.io/files/b440d109-3246-4876-b8aa-aadb290ee06c.json","screenshot_url":"https://uploads-prod.reticulum.io/files/e66ab713-7999-4bb4-9c39-b98e188be6f6.jpg","type":"scene_listing","url":"https://hubs.mozilla.com/scenes/pROJc5X/scrollyroom"}]}
