{"scenes":[{"account_id":false,"allow_promotion":true,"allow_remixing":true,"attribution":null,"attributions":{"content":[],"creator":"JCo"},"description":null,"model_url":"https://uploads-prod.reticulum.io/files/0a95cfe9-202c-4185-b2c3-c885118841aa.bin","name":"Spiral Tower","parent_scene_id":"uNVZeKd","project_id":"2Bdjwsq","scene_id":"63qrHdp","scene_project_url":"https://uploads-prod.reticulum.io/files/0864153c-a37f-4b87-93e6-943ce36945a3.json","screenshot_url":"https://uploads-prod.reticulum.io/files/e1f3878a-4cf7-499e-8a7a-59c987e9bb75.jpg","type":"scene_listing","url":"https://hubs.mozilla.com/scenes/63qrHdp/spiral-tower"}]}
